tparton/__init__.py
tparton/__main__.py
tparton/constants.py
tparton/m_evolution.py
tparton/t_evolution.py
tparton/.ipynb_checkpoints/constants-checkpoint.py
tparton/.ipynb_checkpoints/m_evolution-checkpoint.py
tparton/.ipynb_checkpoints/t_evolution-checkpoint.py
tparton-2.0.0.dist-info/METADATA
tparton-2.0.0.dist-info/WHEEL
tparton-2.0.0.dist-info/licenses/LICENSE
tparton-2.0.0.dist-info/RECORD
