Metadata-Version: 2.4
Name: tparton
Version: 2.0.0
Summary: Evolution of the transversity parton distribution functions via two methods: (1) direct integration of the DGLAP equations along the energy scale and (2) fast Mellin inversion.
Author-email: Congzhou M Sha <cms6712@psu.edu>
License-File: LICENSE
Classifier: License :: OSI Approved :: MIT License
Classifier: Operating System :: OS Independent
Classifier: Programming Language :: Python :: 3
Requires-Python: >=3.8
Requires-Dist: gmpy2
Requires-Dist: mpmath
Requires-Dist: numpy>=1.20
Requires-Dist: scipy>=1.13
